syftbox/__init__.py
syftbox/main.py
syftbox/server2client_version.json
syftbox/app/__init__.py
syftbox/app/cli.py
syftbox/app/install.py
syftbox/app/manager.py
syftbox/assets/icon.zip
syftbox/assets/tui.tcss
syftbox/assets/templates/sync_dashboard.jinja2
syftbox/client/__init__.py
syftbox/client/api.py
syftbox/client/auth.py
syftbox/client/base.py
syftbox/client/cli.py
syftbox/client/core.py
syftbox/client/env.py
syftbox/client/exceptions.py
syftbox/client/logger.py
syftbox/client/plugin_manager.py
syftbox/client/server_client.py
syftbox/client/setup_interactive.py
syftbox/client/benchmark/__init__.py
syftbox/client/benchmark/netstats_http.py
syftbox/client/benchmark/netstats_tcp.py
syftbox/client/benchmark/network.py
syftbox/client/benchmark/report.py
syftbox/client/benchmark/runner.py
syftbox/client/benchmark/sync.py
syftbox/client/benchmark/syncstats.py
syftbox/client/plugins/app_scheduler.py
syftbox/client/plugins/apps.py
syftbox/client/plugins/sync/__init__.py
syftbox/client/plugins/sync/constants.py
syftbox/client/plugins/sync/consumer.py
syftbox/client/plugins/sync/datasite_state.py
syftbox/client/plugins/sync/exceptions.py
syftbox/client/plugins/sync/local_state.py
syftbox/client/plugins/sync/manager.py
syftbox/client/plugins/sync/producer.py
syftbox/client/plugins/sync/queue.py
syftbox/client/plugins/sync/sync_action.py
syftbox/client/plugins/sync/types.py
syftbox/client/routers/app_router.py
syftbox/client/routers/common.py
syftbox/client/routers/datasite_router.py
syftbox/client/routers/index_router.py
syftbox/client/routers/sync_router.py
syftbox/client/utils/__init__.py
syftbox/client/utils/dir_tree.py
syftbox/client/utils/display.py
syftbox/client/utils/error_reporting.py
syftbox/client/utils/file_manager.py
syftbox/client/utils/macos.py
syftbox/client/utils/net.py
syftbox/lib/__init__.py
syftbox/lib/client_config.py
syftbox/lib/client_shim.py
syftbox/lib/constants.py
syftbox/lib/datasite.py
syftbox/lib/debug.py
syftbox/lib/email.py
syftbox-0.4.0.dist-info/METADATA
syftbox-0.4.0.dist-info/WHEEL
syftbox-0.4.0.dist-info/entry_points.txt
syftbox-0.4.0.dist-info/licenses/LICENSE
syftbox-0.4.0.dist-info/RECORD
