Metadata-Version: 2.4
Name: syftbox
Version: 0.4.0
Summary: Add your description here
License-File: LICENSE
Requires-Python: >=3.9
Requires-Dist: aiofiles>=24.1.0
Requires-Dist: croniter==6.0.0
Requires-Dist: curl-cffi==0.10.0
Requires-Dist: distro==1.9.0
Requires-Dist: fastapi==0.115.12
Requires-Dist: gunicorn==23.0.0
Requires-Dist: httpx==0.28.1
Requires-Dist: jinja2==3.1.6
Requires-Dist: loguru==0.7.3
Requires-Dist: msgpack>=1.1.0
Requires-Dist: opentelemetry-exporter-otlp-proto-grpc==1.31.1
Requires-Dist: opentelemetry-instrumentation-fastapi==0.52b1
Requires-Dist: opentelemetry-instrumentation-sqlite3==0.52b1
Requires-Dist: pathspec==0.12.1
Requires-Dist: pid==3.0.4
Requires-Dist: psutil==6.1.1
Requires-Dist: py-fast-rsync==0.1.0
Requires-Dist: pydantic-settings==2.8.1
Requires-Dist: pydantic[email]==2.11.3
Requires-Dist: pyjwt==2.10.1
Requires-Dist: python-multipart==0.0.20
Requires-Dist: pyyaml==6.0.2
Requires-Dist: requests>=2.32.3
Requires-Dist: rich==14.0.0
Requires-Dist: textual==1.0.0
Requires-Dist: tqdm>=4.67.1
Requires-Dist: typer==0.15.2
Requires-Dist: typing-extensions==4.13.1
Requires-Dist: uvicorn==0.34.0
Requires-Dist: wcmatch==10.0
